tumblr_noauth/__init__.py
tumblr_noauth/tumblr_noauth.py
tumblr_noauth-0.1.0.dist-info/METADATA
tumblr_noauth-0.1.0.dist-info/RECORD
tumblr_noauth-0.1.0.dist-info/WHEEL
tumblr_noauth-0.1.0.dist-info/top_level.txt
