Metadata-Version: 2.1
Name: tumblr-noauth
Version: 0.1.0
Summary: A sneaky Tumblr API
Home-page: https://github.com/9999years/tumblr_noauth
Author: Rebecca Turner
Author-email: 637275@gmail.com
License: AGPL-3.0
Keywords: tumblr api
Platform: UNKNOWN
Classifier: Development Status :: 3 - Alpha
Classifier: Intended Audience :: Developers
Classifier: License :: OSI Approved :: GNU Affero General Public License v3
Classifier: Programming Language :: Python :: 3
Requires-Dist: requests
Requires-Dist: beautifulsoup4
